{
    "type": "THROW",
    "inputs": "2+4",
    "visibility": {
        "defense": true
    },
    "frames": {
        "startup": {
            "min": 12
        },
        "hit": {
            "normal": 0
        },
        "escape": {
            "normal-hit": 21,
            "counter-hit": 14
        },
        "after-escape": -3
    },
    "distances": {
        "range": 195,
        "hit": {
            "normal": 184
        },
        "escape": 174
    },
    "escapes": [
        "1",
        "2"
    ],
    "damages": {
        "normal": 35
    }
}
